aesthetics
