Metadata-Version: 1.0
Name: Aesthetics
Version: 0.1.1
Summary: Image Aesthetics Toolkit
Home-page: https://github.com/shubhamchaudhary/aesthetics
Author: Shubham Chaudhary
Author-email: me@shubhamchaudhary.in
License: GPLv3+
Platform: UNKNOWN
